.gitignore
.readthedocs.yml
Dockerfile
LICENSE
README.rst
pyproject.toml
requirements.txt
setup.py
.github/pull_request_template.md
.github/workflows/python-package.yml
JOSS-paper/paper.bib
JOSS-paper/paper.md
examples/airy.py
examples/burst.cpp
examples/cosmology.ipynb
examples/introduction_to_pyoscode.ipynb
examples/plot_burst.py
examples/pyoscode_scipy.ipynb
examples/test-rk.py
examples/images/airy.png
examples/images/bingo-singlek-k1e-5-ref.txt
examples/images/bingo-singlek-k1e-5.txt
examples/images/cambridge.png
examples/images/caplogo.svg
examples/images/cmb.png
examples/images/kavli.jpg
examples/images/rkwkb-single-k1e-5.txt
examples/images/singlek-kd-bd-2a.txt
examples/images/singlek-kd-bg-2a-ref.txt
include/interpolator.hpp
include/rksolver.hpp
include/solver.hpp
include/system.hpp
include/wkbsolver.hpp
include/Eigen/Cholesky
include/Eigen/CholmodSupport
include/Eigen/Core
include/Eigen/Dense
include/Eigen/Eigen
include/Eigen/Eigenvalues
include/Eigen/Geometry
include/Eigen/Householder
include/Eigen/IterativeLinearSolvers
include/Eigen/Jacobi
include/Eigen/LU
include/Eigen/MetisSupport
include/Eigen/OrderingMethods
include/Eigen/PaStiXSupport
include/Eigen/PardisoSupport
include/Eigen/QR
include/Eigen/QtAlignedMalloc
include/Eigen/SPQRSupport
include/Eigen/SVD
include/Eigen/Sparse
include/Eigen/SparseCholesky
include/Eigen/SparseCore
include/Eigen/SparseLU
include/Eigen/SparseQR
include/Eigen/StdDeque
include/Eigen/StdList
include/Eigen/StdVector
include/Eigen/SuperLUSupport
include/Eigen/UmfPackSupport
include/Eigen/src/Cholesky/LDLT.h
include/Eigen/src/Cholesky/LLT.h
include/Eigen/src/Cholesky/LLT_LAPACKE.h
include/Eigen/src/CholmodSupport/CholmodSupport.h
include/Eigen/src/Core/Array.h
include/Eigen/src/Core/ArrayBase.h
include/Eigen/src/Core/ArrayWrapper.h
include/Eigen/src/Core/Assign.h
include/Eigen/src/Core/AssignEvaluator.h
include/Eigen/src/Core/Assign_MKL.h
include/Eigen/src/Core/BandMatrix.h
include/Eigen/src/Core/Block.h
pyoscode.egg-info/PKG-INFO
pyoscode.egg-info/SOURCES.txt
pyoscode.egg-info/dependency_links.txt
pyoscode.egg-info/requires.txt
pyoscode.egg-info/top_level.txt
