Metadata-Version: 2.1
Name: pyoscode
Version: 1.1.2
Summary: oscode: Oscillatory ordinary differential equation solver
Home-page: https://github.com/fruzsinaagocs/oscode
Author: Fruzsina Agocs
Author-email: fa325@cam.ac.uk
License: oscode
Project-URL: Documentation, https://oscode.readthedocs.io
Keywords: PPS,cosmic inflation,cosmology,oscillatory,ODE
Classifier: Intended Audience :: Developers
Classifier: Intended Audience :: Science/Research
Classifier: Natural Language :: English
Classifier: Programming Language :: Python :: 3.4
Classifier: Programming Language :: Python :: 3.5
Classifier: Programming Language :: Python :: 3.6
Classifier: Programming Language :: Python :: 3.7
Classifier: Topic :: Scientific/Engineering
Classifier: Topic :: Scientific/Engineering :: Astronomy
Classifier: Topic :: Scientific/Engineering :: Physics
Classifier: Topic :: Scientific/Engineering :: Visualization
Classifier: Topic :: Scientific/Engineering :: Mathematics
Provides-Extra: examples
Provides-Extra: docs
Provides-Extra: testing
License-File: LICENSE
